shipyard_postgresql/__init__.py
shipyard_postgresql/cli/__init__.py
shipyard_postgresql/cli/authtest.py
shipyard_postgresql/cli/execute_sql.py
shipyard_postgresql/cli/store_query_results.py
shipyard_postgresql/cli/upload_file.py
shipyard_postgresql/postgres.py
shipyard_postgresql-0.2.0.dist-info/METADATA
shipyard_postgresql-0.2.0.dist-info/WHEEL
shipyard_postgresql-0.2.0.dist-info/RECORD
